Metadata-Version: 1.0
Name: dsuc
Version: 0.2
Summary: Gaussian and Binomial distributions
Home-page: UNKNOWN
Author: Ieva Dirdaite
Author-email: ieva.dirdaite@gmail.com
License: UNKNOWN
Platform: UNKNOWN
